bigdl/cpp/__init__.py
bigdl/cpp/convert_hf_to_gguf.py
bigdl/cpp/convert_hf_to_gguf_update.py
bigdl/cpp/convert_llama_ggml_to_gguf.py
bigdl/cpp/convert_lora_to_gguf.py
bigdl/cpp/cli/init-llama-cpp
bigdl/cpp/cli/init-ollama
bigdl/cpp/gguf-py/__init__.py
bigdl/cpp/gguf-py/gguf/__init__.py
bigdl/cpp/gguf-py/gguf/constants.py
bigdl/cpp/gguf-py/gguf/gguf.py
bigdl/cpp/gguf-py/gguf/gguf_reader.py
bigdl/cpp/gguf-py/gguf/gguf_writer.py
bigdl/cpp/gguf-py/gguf/lazy.py
bigdl/cpp/gguf-py/gguf/metadata.py
bigdl/cpp/gguf-py/gguf/py.typed
bigdl/cpp/gguf-py/gguf/quants.py
bigdl/cpp/gguf-py/gguf/tensor_mapping.py
bigdl/cpp/gguf-py/gguf/utility.py
bigdl/cpp/gguf-py/gguf/vocab.py
bigdl/cpp/libs/libggml-base.so
bigdl/cpp/libs/libggml-cpu.so
bigdl/cpp/libs/libggml-sycl.so
bigdl/cpp/libs/libggml.so
bigdl/cpp/libs/libllama.so
bigdl/cpp/libs/libllava_shared.so
bigdl/cpp/libs/libmllama.so
bigdl/cpp/libs/libollama-ggml-base.so
bigdl/cpp/libs/libollama-ggml-cpu.so
bigdl/cpp/libs/libollama-ggml-sycl.so
bigdl/cpp/libs/libollama_ggml.so
bigdl/cpp/libs/libollama_llama.so
bigdl/cpp/libs/libollama_llava_shared.so
bigdl/cpp/libs/libsample.so
bigdl/cpp/libs/llama-batched
bigdl/cpp/libs/llama-bench
bigdl/cpp/libs/llama-cli
bigdl/cpp/libs/llama-embedding
bigdl/cpp/libs/llama-gemma3-cli
bigdl/cpp/libs/llama-gguf
bigdl/cpp/libs/llama-llava-cli
bigdl/cpp/libs/llama-lookup
bigdl/cpp/libs/llama-ls-sycl-device
bigdl/cpp/libs/llama-minicpmv-cli
bigdl/cpp/libs/llama-perplexity
bigdl/cpp/libs/llama-quantize
bigdl/cpp/libs/llama-server
bigdl/cpp/libs/llama-simple
bigdl/cpp/libs/llama-speculative
bigdl/cpp/libs/llama-tokenize
bigdl/cpp/libs/ollama
bigdl/cpp/libs/ollama-lib
bigdl_core_cpp-2.6.0.data/scripts/init-llama-cpp
bigdl_core_cpp-2.6.0.data/scripts/init-ollama
bigdl_core_cpp-2.6.0.dist-info/METADATA
bigdl_core_cpp-2.6.0.dist-info/WHEEL
bigdl_core_cpp-2.6.0.dist-info/top_level.txt
bigdl_core_cpp-2.6.0.dist-info/RECORD
