Metadata-Version: 2.4
Name: bigdl-core-cpp
Version: 2.6.0
Summary: Large Language Model Develop Toolkit
Author: BigDL Authors
License: Apache License, Version 2.0
Classifier: License :: OSI Approved :: Apache Software License
Classifier: Programming Language :: Python :: 3
Classifier: Programming Language :: Python :: 3.9
Classifier: Programming Language :: Python :: Implementation :: CPython
Requires-Dist: torch==2.2.0
Requires-Dist: numpy==1.26.4
Requires-Dist: transformers==4.44.2
Requires-Dist: sentencepiece~=0.1.98
Requires-Dist: accelerate==0.33.0
Requires-Dist: protobuf<5.0.0,>=4.21.0
Requires-Dist: gguf>=0.1.0
Dynamic: author
Dynamic: classifier
Dynamic: license
Dynamic: requires-dist
Dynamic: summary
